{
  "1yr": {
    "totalRet": 70.79,
    "annRet": 63.9,
    "mdd": -3.05,
    "vol": 18.59,
    "sharpe": 3.3,
    "winRate": 60.0,
    "trades": 45,
    "months": 13,
    "start": "25-03",
    "end": "26-03"
  },
  "3yr": {
    "totalRet": 78.3,
    "annRet": 20.63,
    "mdd": -7.49,
    "vol": 14.49,
    "sharpe": 1.25,
    "winRate": 51.8,
    "trades": 85,
    "months": 37,
    "start": "23-03",
    "end": "26-03"
  },
  "5yr": {
    "totalRet": 150.64,
    "annRet": 19.81,
    "mdd": -7.5,
    "vol": 14.5,
    "sharpe": 1.19,
    "winRate": 55.2,
    "trades": 105,
    "months": 61,
    "start": "21-03",
    "end": "26-03"
  }
}